{
  "CONDITIONATTR_TYPE": 1,
  "CONDITIONATTR_ID": 2,
  "CONDITIONATTR_TICKS": 3,
  "CONDITIONATTR_HEALTHTICKS": 4,
  "CONDITIONATTR_HEALTHGAIN": 5,
  "CONDITIONATTR_MANATICKS": 6,
  "CONDITIONATTR_MANAGAIN": 7,
  "CONDITIONATTR_DELAYED": 8,
  "CONDITIONATTR_OWNER": 9,
  "CONDITIONATTR_INTERVALDATA": 10,
  "CONDITIONATTR_SPEEDDELTA": 11,
  "CONDITIONATTR_FORMULA_MINA": 12,
  "CONDITIONATTR_FORMULA_MINB": 13,
  "CONDITIONATTR_FORMULA_MAXA": 14,
  "CONDITIONATTR_FORMULA_MAXB": 15,
  "CONDITIONATTR_LIGHTCOLOR": 16,
  "CONDITIONATTR_LIGHTLEVEL": 17,
  "CONDITIONATTR_LIGHTTICKS": 18,
  "CONDITIONATTR_LIGHTINTERVAL": 19,
  "CONDITIONATTR_SOULTICKS": 20,
  "CONDITIONATTR_SOULGAIN": 21,
  "CONDITIONATTR_SKILLS": 22,
  "CONDITIONATTR_STATS": 23,
  "CONDITIONATTR_OUTFIT": 24,
  "CONDITIONATTR_PERIODDAMAGE": 25,
  "CONDITIONATTR_ISBUFF": 26,
  "CONDITIONATTR_SUBID": 27,
  "CONDITIONATTR_ISAGGRESSIVE": 28,
  "CONDITIONATTR_DISABLEDEFENSE": 29,
  "CONDITIONATTR_SPECIALSKILLS": 30,
  "CONDITIONATTR_MANASHIELD_BREAKABLE_MANA": 31,
  "CONDITIONATTR_MANASHIELD_BREAKABLE_MAXMANA": 32,
  "CONDITIONATTR_END": 254
}